{
    "fermate": [
      {
        "id": 1,
        "nome": "Trento",
        "coordinate": [46.07242770533295, 11.119415716482608]
      },
      {
        "id": 2,
        "nome": "Rovereto",
        "coordinate": [45.89131970702547, 11.034080469883865]
      },
      {
        "id": 3,
        "nome": "Ala",
        "coordinate": [45.75921224984683, 10.996474139192028]
      },
      {
        "id": 4,
        "nome": "Domegliara",
        "coordinate": [45.52250619300174, 10.820713110343668]
      },
      {
        "id": 5,
        "nome": "Verona",
        "coordinate": [45.42930095695064, 10.982438965629317]
      }
    ]
  }
  